CHANGES.txt
CONTRIBUTORS.txt
MANIFEST.in
README.txt
setup.py
collective/__init__.py
collective.recaptchawidget.egg-info/PKG-INFO
collective.recaptchawidget.egg-info/SOURCES.txt
collective.recaptchawidget.egg-info/dependency_links.txt
collective.recaptchawidget.egg-info/entry_points.txt
collective.recaptchawidget.egg-info/namespace_packages.txt
collective.recaptchawidget.egg-info/not-zip-safe
collective.recaptchawidget.egg-info/paster_plugins.txt
collective.recaptchawidget.egg-info/requires.txt
collective.recaptchawidget.egg-info/top_level.txt
collective/recaptchawidget/README.txt
collective/recaptchawidget/VERSION.txt
collective/recaptchawidget/__init__.py
collective/recaptchawidget/config.py
collective/recaptchawidget/configure.zcml
collective/recaptchawidget/field.py
collective/recaptchawidget/validators.py
collective/recaptchawidget/widget.py
collective/recaptchawidget/browser/__init__.py
collective/recaptchawidget/browser/configure.zcml
collective/recaptchawidget/content/__init__.py
collective/recaptchawidget/content/configure.zcml
collective/recaptchawidget/content/recaptchaedcontent.py
collective/recaptchawidget/interfaces/__init__.py
collective/recaptchawidget/interfaces/recaptchaedcontent.py
collective/recaptchawidget/profiles/default/factorytool.xml
collective/recaptchawidget/profiles/default/metadata.xml
collective/recaptchawidget/profiles/default/rolemap.xml
collective/recaptchawidget/profiles/default/skins.xml
collective/recaptchawidget/profiles/default/types.xml
collective/recaptchawidget/profiles/default/types/Recaptchaed_Content.xml
collective/recaptchawidget/skins/recaptchawidget/recaptchawidget.pt
collective/recaptchawidget/tests/__init__.py
collective/recaptchawidget/tests/base.py
collective/recaptchawidget/tests/test_doctest.py
docs/HISTORY.txt
docs/INSTALL.txt
docs/LICENSE.GPL
docs/LICENSE.txt