Metadata-Version: 1.0
Name: collective.recaptchawidget
Version: 0.5
Summary: A simple widget that uses collective.recaptcha for Archetypes
Home-page: http://svn.plone.org/svn/collective/
Author: Carlos de la Guardia
Author-email: cguardia@yahoo.com
License: GPL
Platform: UNKNOWN
Classifier: Framework :: Plone
Classifier: Intended Audience :: Developers
Classifier: License :: OSI Approved :: GNU General Public License (GPL)
